{
  "public_identifier": "tim-waldron-00090757",
  "profile_pic_url": "https://assets.enrichlayer.com/pp/profilepic/b7c207250f0a7c47ef602bbfd9d4d006",
  "background_cover_image_url": "https://assets.enrichlayer.com/pp/profilepic/60c6015ee2519c056444fbd033145b42",
  "first_name": "Tim",
  "last_name": "Waldron",
  "full_name": "Tim Waldron",
  "follower_count": 2248,
  "occupation": "Strategy Lead, EMEA at DPAA, The Global Out of Home Association",
  "headline": "Executive Director, EMEA, DPAA - The Global Out of Home Association",
  "summary": "Tim joined Haymarket  in 1989 in London in media sales. In 2000 he moved to Singapore to launch CEI Asia Pacific for Haymarket. In 2001 he took up the role of Managing Director of Haymarket’s Asian businesses, including China, based in Hong Kong, with responsibility for Haymarket’s portfolio of publications, websites, conference and awards within the region. Tim was Co Chairman of Spikes Asia Festival, a joint venture between Haymarket and Ascential the organisers of Cannes Lions.<br><br>Tim joined Asian Integrated Media in April 2019 as Chief Executive and retains the role of Executive Director.<br><br>In October 2022, Tim took on the role of Strategy Lead, EMEA for DPAA, the Global Digital Out of Home Association.<br> <br> <br>",
  "location_str": "United Kingdom",
  "country": "GB",
  "country_full_name": "United Kingdom",
  "city": null,
  "state": null,
  "experiences": [
    {
      "starts_at": {
        "day": 1,
        "month": 10,
        "year": 2022
      },
      "ends_at": null,
      "company": "DPAA, The Global Out of Home Association",
      "company_linkedin_profile_url": null,
      "company_facebook_profile_url": null,
      "title": "Strategy Lead, EMEA",
      "description": null,
      "location": "United Kingdom",
      "logo_url": null
    },
    {
      "starts_at": {
        "day": 1,
        "month": 3,
        "year": 2019
      },
      "ends_at": {
        "day": 31,
        "month": 10,
        "year": 2022
      },
      "company": "Asian Integrated Media Limited",
      "company_linkedin_profile_url": null,
      "company_facebook_profile_url": null,
      "title": "Executive Director",
      "description": null,
      "location": "Hong Kong",
      "logo_url": null
    },
    {
      "starts_at": {
        "day": 1,
        "month": 3,
        "year": 1989
      },
      "ends_at": {
        "day": 31,
        "month": 7,
        "year": 2018
      },
      "company": "Haymarket Media Group",
      "company_linkedin_profile_url": "https://www.linkedin.com/company/haymarket-media-group",
      "company_facebook_profile_url": null,
      "title": "Managing Director",
      "description": null,
      "location": "Asia",
      "logo_url": "https://assets.enrichlayer.com/pp/profilepic/3b6fa9517bd34b0412e5f96740add98d"
    }
  ],
  "education": [
    {
      "starts_at": null,
      "ends_at": null,
      "field_of_study": null,
      "degree_name": null,
      "school": "Kings School Rochester",
      "school_linkedin_profile_url": null,
      "school_facebook_profile_url": null,
      "description": null,
      "logo_url": null,
      "grade": null,
      "activities_and_societies": null
    }
  ],
  "languages": [],
  "languages_and_proficiencies": [],
  "accomplishment_organisations": [],
  "accomplishment_publications": [],
  "accomplishment_honors_awards": [],
  "accomplishment_patents": [],
  "accomplishment_courses": [],
  "accomplishment_projects": [],
  "accomplishment_test_scores": [],
  "volunteer_work": [],
  "certifications": [],
  "connections": 2245,
  "people_also_viewed": [
    {
      "link": "https://www.linkedin.com/in/simoncf",
      "name": "Simon Lee",
      "summary": "Essayist | Classical Liberal | Hong Konger | Geek | Stoic | Agnostic | Chaotic Neutral",
      "location": "Fairfax"
    },
    {
      "link": "https://www.linkedin.com/in/betharcher789",
      "name": "Beth Archer",
      "summary": "Head of Operations",
      "location": "Chatham"
    },
    {
      "link": "https://www.linkedin.com/in/debbiebenadiba",
      "name": "Debbie Benadiba",
      "summary": "CEO of Talon OOH Canada | Digital Media Innovation | Future of Adtech & OOH | Empowering Women Leadership | Board Member",
      "location": "Toronto"
    },
    {
      "link": "https://www.linkedin.com/in/tamaraessex",
      "name": "Tamara Essex",
      "summary": null,
      "location": "Salisbury"
    },
    {
      "link": "https://www.linkedin.com/in/jinnykwon",
      "name": "권현진",
      "summary": "문제를 해결하는 스타트업 그로스 마케팅 전문가 | 퍼포먼스, 콘텐츠, SEO",
      "location": "Seoul"
    },
    {
      "link": "https://www.linkedin.com/in/domkozak",
      "name": "Dom Kozak",
      "summary": "Head of Programmatic at JCDecaux UK",
      "location": "London"
    },
    {
      "link": "https://www.linkedin.com/in/ray-yu-27377ab4",
      "name": "Ray Yu",
      "summary": "Director",
      "location": ""
    },
    {
      "link": "https://www.linkedin.com/in/yudisoetjiptadi",
      "name": "Yudi Soetjiptadi",
      "summary": "Founder & CEO at Eventus International",
      "location": "Oxford"
    },
    {
      "link": "https://www.linkedin.com/in/dearden",
      "name": "Matthew Dearden",
      "summary": "CEO, entrepreneur, and adviser",
      "location": "London"
    },
    {
      "link": "https://www.linkedin.com/in/john-manning-27b28b1bb",
      "name": "John Manning",
      "summary": "Student at Holcombe Grammar School",
      "location": "Hoo St Werburgh"
    },
    {
      "link": "https://www.linkedin.com/in/benmaher",
      "name": "Ben Maher",
      "summary": null,
      "location": "London"
    },
    {
      "link": "https://www.linkedin.com/in/janelle-hyman-advertising-communications-specialist",
      "name": "Janelle H.",
      "summary": "Experienced Advertising Sales Leader | 13+ Years Multi-Platform Ad Sales | New Business Development | Former New Media Sales Manager",
      "location": "Richmond"
    },
    {
      "link": "https://www.linkedin.com/in/seanleedavies88",
      "name": "Sean Davies",
      "summary": "Conscious Leadership & Longevity Mentor ⚡ 3× TEDx Speaker | Helping Founders & Visionaries Master Energy, Purpose & Peak Performance | Host of The Conscious Rising | Founder CEO, Awethentic Group & The Conscious Festival",
      "location": "Hong Kong"
    },
    {
      "link": "https://www.linkedin.com/in/jonathan-hirst-realfin",
      "name": "Jonathan Hirst",
      "summary": "Commercial Director, Financial Information & Media",
      "location": "Hong Kong"
    },
    {
      "link": "https://www.linkedin.com/in/tom-saunders-965599137",
      "name": "Tom Saunders",
      "summary": null,
      "location": "Rochester"
    },
    {
      "link": "https://www.linkedin.com/in/henry-wong-ceo-and-founder-of-ideology-group-9a666252",
      "name": "Henry Wong CEO and Founder Of Ideology Group",
      "summary": "Branch Manager of AIA International Limited, Hong Kong",
      "location": ""
    },
    {
      "link": "https://www.linkedin.com/in/carolineturnerrecruiter",
      "name": "Caroline Turner",
      "summary": null,
      "location": "London"
    },
    {
      "link": "https://www.linkedin.com/in/limecreativehk",
      "name": "Bill mcqueen",
      "summary": "Founder/Chief Content Officer at Lime* Content Studios | Broadcast Industry Veteran  Award Winning Creative. Co-founder Pixel Juice",
      "location": "Hong Kong"
    },
    {
      "link": "https://www.linkedin.com/in/brendaninns",
      "name": "Brendan Inns",
      "summary": "Media Advertising Specialist | Proptech Entrepreneur | Co-founder, FIND",
      "location": ""
    },
    {
      "link": "https://www.linkedin.com/in/andrewwork",
      "name": "Andrew Work",
      "summary": null,
      "location": ""
    },
    {
      "link": "https://www.linkedin.com/in/helena-choe-525884",
      "name": "Helena Choe",
      "summary": "SVP, Media Sales",
      "location": ""
    },
    {
      "link": "https://www.linkedin.com/in/richard-brooke-0715152",
      "name": "Richard Brooke",
      "summary": "Global Media Operations Director at Unilever",
      "location": "Ashtead"
    },
    {
      "link": "https://www.linkedin.com/in/simon-durrant-429b903",
      "name": "simon durrant",
      "summary": null,
      "location": ""
    },
    {
      "link": "https://www.linkedin.com/in/helshi-lockwood-tunnell-hewson-b238504",
      "name": "Helshi Lockwood Tunnell Hewson",
      "summary": "Retired, Director, Print Media, Partnership to End Addiction",
      "location": "Darien"
    },
    {
      "link": "https://www.linkedin.com/in/yukari-ogawa-642b664",
      "name": "Yukari Ogawa",
      "summary": "Manager, Media Coordination & Research at LVMH Moet Hennessy - Louis Vuitton Japan K.K.",
      "location": ""
    },
    {
      "link": "https://www.linkedin.com/in/ian-ashcroft-6474455",
      "name": "Ian Ashcroft",
      "summary": "Executive Director",
      "location": "London"
    },
    {
      "link": "https://www.linkedin.com/in/todd-miller-76994a6",
      "name": "Todd Miller",
      "summary": "Best-selling Author | Adventurer | Work-Life Evangelist",
      "location": ""
    },
    {
      "link": "https://www.linkedin.com/in/scott-thoreau-7991377",
      "name": "Scott Thoreau",
      "summary": "Founder/Director, Camisa Ltd.",
      "location": "Hong Kong"
    },
    {
      "link": "https://www.linkedin.com/in/graham-newall-7b36499",
      "name": "Graham Newall",
      "summary": "Chairman Planet Media Ltd ,\nCEO IOWN LLC, CEO Pay Caesar Ltd, CEO DCX Technology LTD",
      "location": "Darling Heights"
    },
    {
      "link": "https://www.linkedin.com/in/juliana-mattar-a30177a",
      "name": "Juliana Mattar",
      "summary": "Founder and CEO at Motion: For Impact",
      "location": ""
    },
    {
      "link": "https://www.linkedin.com/in/rupert-walker-213b03a",
      "name": "Rupert Walker",
      "summary": "Editor Asia, MA Financial Media",
      "location": ""
    },
    {
      "link": "https://www.linkedin.com/in/gary-dooley-0485b210",
      "name": "Gary Dooley",
      "summary": "Director of Development at Rank Group retired",
      "location": "Milton Keynes"
    },
    {
      "link": "https://www.linkedin.com/in/stephanie-staten-814a8911",
      "name": "Stephanie Staten",
      "summary": "Marketing Coordinator & Graphic Designer",
      "location": "Queens"
    },
    {
      "link": "https://www.linkedin.com/in/nancy-song-30088916",
      "name": "Nancy Song",
      "summary": null,
      "location": ""
    },
    {
      "link": "https://www.linkedin.com/in/stella-berry-toma-80999518",
      "name": "Stella Berry (Toma)",
      "summary": "Senior Global Industry Director: Beauty & Luxury @ Teads | Advertising, Luxury Brands",
      "location": ""
    },
    {
      "link": "https://www.linkedin.com/in/sean-lee-davies-64817920",
      "name": "Sean Davies",
      "summary": "Conscious Leadership l CEO & Chairman Green Is The New Black & The Conscious Festival | Founder & CEO of Awethentic Group and Project C:CHANGE",
      "location": "Hong Kong"
    },
    {
      "link": "https://www.linkedin.com/in/purple-ho-97595720",
      "name": "Purple Ho",
      "summary": "General manager at Emperor Entertainment Group",
      "location": ""
    },
    {
      "link": "https://www.linkedin.com/in/weicheng-liu-b4201721",
      "name": "Weicheng Liu",
      "summary": "Executive at YOU On Demand",
      "location": "Shanghai"
    },
    {
      "link": "https://www.linkedin.com/in/joseph-yap-98557b24",
      "name": "Joseph Yap",
      "summary": null,
      "location": ""
    },
    {
      "link": "https://www.linkedin.com/in/cindy-chan-99518827",
      "name": "Cindy Chan",
      "summary": "Art Director",
      "location": ""
    },
    {
      "link": "https://www.linkedin.com/in/robert-benjamin-b2714829",
      "name": "Robert Benjamin",
      "summary": "Property buyer and private lender",
      "location": ""
    },
    {
      "link": "https://www.linkedin.com/in/adam-powell-5a8b8729",
      "name": "Adam Powell",
      "summary": "Subject Matter Expert: Location Intelligence at Adsquare",
      "location": "London"
    },
    {
      "link": "https://www.linkedin.com/in/shaun-wing-hei-hui-6b84502b",
      "name": "Shaun Wing Hei Hui",
      "summary": "Marketing and Communication Director at Bulgari",
      "location": ""
    },
    {
      "link": "https://www.linkedin.com/in/chia-sam-a7157630",
      "name": "chia sam",
      "summary": null,
      "location": "Beijing"
    },
    {
      "link": "https://www.linkedin.com/in/charmaine-li-09869b35",
      "name": "Charmaine Li",
      "summary": "Joint CEO at The Kowloon Dairy Limited",
      "location": ""
    },
    {
      "link": "https://www.linkedin.com/in/david-wu-276ab03b",
      "name": "david wu",
      "summary": "General Manager at IST Media",
      "location": ""
    },
    {
      "link": "https://www.linkedin.com/in/helen-mok-64905240",
      "name": "Helen Mok",
      "summary": null,
      "location": ""
    },
    {
      "link": "https://www.linkedin.com/in/marjorie-mok-80a49b43",
      "name": "Marjorie Mok",
      "summary": "Business Travel Coordinator at Haymarket Media Asia",
      "location": ""
    },
    {
      "link": "https://www.linkedin.com/in/rebecca-yuen-16589044",
      "name": "Rebecca Yuen",
      "summary": "General Manager, Hong Kong at George P Johnson Experience Marketing",
      "location": ""
    },
    {
      "link": "https://www.linkedin.com/in/jim-nicastro-44793a48",
      "name": "Jim Nicastro",
      "summary": "exec vp at StayHealthy",
      "location": "Los Angeles"
    },
    {
      "link": "https://www.linkedin.com/in/nicole-lonsdale-33508151",
      "name": "Nicole Lonsdale",
      "summary": null,
      "location": ""
    },
    {
      "link": "https://www.linkedin.com/in/rachel-tan-73861253",
      "name": "Rachel Tan",
      "summary": "Assistant Mgr at Singapore Airlines",
      "location": ""
    },
    {
      "link": "https://www.linkedin.com/in/corine-ruelle-85598356",
      "name": "Corine Ruelle",
      "summary": "Director at Staggered Trading Ltd",
      "location": "Rochester"
    },
    {
      "link": "https://www.linkedin.com/in/wolfram-diener-3a406b5a",
      "name": "Wolfram Diener",
      "summary": "President & CEO of Messe Düsseldorf Group",
      "location": "Düsseldorf"
    },
    {
      "link": "https://www.linkedin.com/in/maggie-l-y-ng-05b0a064",
      "name": "Maggie L.Y. Ng",
      "summary": "Senior Event Operations Manager at Haymarket Media Group",
      "location": ""
    },
    {
      "link": "https://www.linkedin.com/in/diana-hui-b1112168",
      "name": "Diana Hui",
      "summary": null,
      "location": ""
    },
    {
      "link": "https://www.linkedin.com/in/meyan-nanguy-6b762674",
      "name": "Meyan NANGUY",
      "summary": "Child Nursing Student",
      "location": "London"
    },
    {
      "link": "https://www.linkedin.com/in/kevin-costello-296ba479",
      "name": "Kevin Costello",
      "summary": "CEO at Haymarket Media Group",
      "location": "London"
    },
    {
      "link": "https://www.linkedin.com/in/catt-simply-50242880",
      "name": "Catt Simply",
      "summary": "Dream Director",
      "location": ""
    },
    {
      "link": "https://www.linkedin.com/in/lucy-delacherois-day-45a955a0",
      "name": "Lucy Delacherois Day",
      "summary": "Global Senior Director of Product - lifestyle",
      "location": ""
    },
    {
      "link": "https://www.linkedin.com/in/nathan-yu-27377ab4",
      "name": "Nathan Yu",
      "summary": "Director",
      "location": ""
    },
    {
      "link": "https://www.linkedin.com/in/penny-brotherton-b2a087104",
      "name": "Penny Brotherton",
      "summary": null,
      "location": "Brighouse"
    },
    {
      "link": "https://www.linkedin.com/in/liang-liang-soh-73ba38123",
      "name": "Liang Liang Soh",
      "summary": null,
      "location": ""
    },
    {
      "link": "https://www.linkedin.com/in/anh-pham-0b1852124",
      "name": "Anh Pham",
      "summary": "M.S. in Electrical Engineering, specialized in Digital Communication and DSP.",
      "location": "Berkeley"
    },
    {
      "link": "https://www.linkedin.com/in/ben-maclaren-9523ba13b",
      "name": "Ben MacLaren",
      "summary": "Head of Media Planning at Sky UK",
      "location": "London"
    },
    {
      "link": "https://www.linkedin.com/in/dimitri-nouchet-05200220b",
      "name": "Dimitri Nouchet",
      "summary": "Étudiant chez Heip, OMNES group",
      "location": "Lyon"
    },
    {
      "link": "https://www.linkedin.com/in/aimee-mckay-26614957",
      "name": "Aimee McKay",
      "summary": "Client Partnership Director & Europe Lead",
      "location": null
    },
    {
      "link": "https://www.linkedin.com/in/jeffreywgriffin",
      "name": "Jeff Griffin",
      "summary": "Global Growth Leader, Advisor, & Nonprofit Board Member | $555M in 4 combined exits ",
      "location": null
    },
    {
      "link": "https://www.linkedin.com/in/dan-durling-2045bb9",
      "name": "Dan Durling",
      "summary": "Chief Operating Officer at Alight Media | ex Yahoo | ex Global Media & Entertainment | making a positive difference by connecting brands and communities in the real world",
      "location": null
    },
    {
      "link": "https://www.linkedin.com/in/gavinwrightrsm",
      "name": "Gavin Wright",
      "summary": "Director of Operations (Skratch)",
      "location": null
    },
    {
      "link": "https://www.linkedin.com/in/baoli-zhao-40857a4",
      "name": "Baoli Zhao",
      "summary": "Founder & MD | On a mission to innovate fresh digital solutions 💡🌐🤝",
      "location": null
    },
    {
      "link": "https://www.linkedin.com/in/gareth-prest-95543aa6",
      "name": "Gareth Prest",
      "summary": "Director - Client Partnerships - Wilkins Media",
      "location": null
    },
    {
      "link": "https://www.linkedin.com/in/rick-robinson",
      "name": "Rick Robinson",
      "summary": "CEO @ PJX Media | OOH Advertising Expert",
      "location": null
    },
    {
      "link": "https://www.linkedin.com/in/susiemcavoy",
      "name": "Susie McAvoy",
      "summary": "Managing Director",
      "location": null
    },
    {
      "link": "https://www.linkedin.com/in/nick-parker-8383467",
      "name": "Nick Parker",
      "summary": "Founder Go2OOH Consultancy Ltd. NED, Chair VIOOH, Global President Veridooh, Former Global COO Kinetic Worldwide - Global OOH Advocate",
      "location": null
    },
    {
      "link": "https://www.linkedin.com/in/bernd-hofstoetter-7127604",
      "name": "Bernd Hofstoetter",
      "summary": "Digital | Media | Music | Scent | Instore | International | Technology",
      "location": null
    },
    {
      "link": "https://www.linkedin.com/in/nikkishack",
      "name": "Nikki Shack",
      "summary": "Experienced recruiter for the Media sector. Director of Harrison Dear Sales, Director of Harrison Dear Elevate",
      "location": null
    },
    {
      "link": "https://www.linkedin.com/in/kashifdalvi",
      "name": "Kashif Dalvi",
      "summary": "Head of Strategy, Europe ",
      "location": null
    },
    {
      "link": "https://www.linkedin.com/in/barryfrey1",
      "name": "Barry Frey",
      "summary": "President and CEO @ DPAA | Industry Digital Leadership",
      "location": null
    },
    {
      "link": "https://www.linkedin.com/in/markleadbitter54994b114",
      "name": "Mark Leadbitter",
      "summary": "Director",
      "location": null
    },
    {
      "link": "https://www.linkedin.com/in/jessica-jones-a6824752",
      "name": "Jessica Jones",
      "summary": "Retail Media Professional, Experienced in \nOps and Execution and \nDigital Proposition",
      "location": null
    },
    {
      "link": "https://www.linkedin.com/in/chrisforrester",
      "name": "Chris Forrester",
      "summary": "Commercial Leader / Qualified Coach / Mentor /  Board Trustee",
      "location": null
    },
    {
      "link": "https://www.linkedin.com/in/adam-jackson-1a06721b3",
      "name": "Adam Jackson",
      "summary": "Business Development Manager - The Student Marketing Company | Multichannel Marketing Specialist: OOH | Sampling | University Welcome Packs | Events | Digital Marketing",
      "location": null
    },
    {
      "link": "https://www.linkedin.com/in/alexkopfliinspired17",
      "name": "Alex Kopfli",
      "summary": "Director - Inspired | Expert in Strategic Sampling Campaigns & Experiential Activations \n",
      "location": null
    },
    {
      "link": "https://www.linkedin.com/in/giancarlo-gambardella-64954b26",
      "name": "Giancarlo Gambardella",
      "summary": "Head of Home and Property @JWE Media \n- Media Planning & Buying\nManaging Director of Howard & Co Attire - Fashion",
      "location": null
    }
  ],
  "recommendations": [],
  "activities": [
    {
      "title": "This year during POSSIBLE our DPAA member, HELI-D is flying high above the Miami skyline! We're running DPAA content on these screens all week so…",
      "link": "https://www.linkedin.com/posts/barryfrey1_lookup-dooh-launchpadofinnovation-activity-7454951866976817152-HdDy",
      "activity_status": null
    },
    {
      "title": "An eye opening media tour of Tenpin Ltd (part of Ten Entertainment Ltd) kindly arranged by Retail Media Revolution. As brands increasingly seek to…",
      "link": "https://www.linkedin.com/posts/roy-shepherd-90086122_ooh-activity-7455296302998921216-bIWz",
      "activity_status": null
    },
    {
      "title": "Great to see Deel live at LCY with a large-format wall wrap in the departure lounge, spanning the retail and duty free area. Set within one of the…",
      "link": "https://www.linkedin.com/posts/london-city-airport-media-sales-568a8017a_airportmedia-dooh-ooh-activity-7454846017113436160-F7ZP",
      "activity_status": null
    },
    {
      "title": "Whether it’s families, EV drivers or affluent audiences, our campaigns can adapt in real time to reflect who is actually present. Our ANPR platform…",
      "link": "https://www.linkedin.com/posts/i-mediaooh_whether-its-families-ev-drivers-or-affluent-activity-7449773509876154368-itw_",
      "activity_status": null
    },
    {
      "title": "First day of Ruby’s work experience in London - courtesy of the lovely Sam Austin, who’s arranged an exciting week for her at the capital’s most…",
      "link": "https://www.linkedin.com/posts/roy-shepherd-90086122_first-day-of-rubys-work-experience-in-london-activity-7454421352838623232-gUhC",
      "activity_status": null
    },
    {
      "title": "Salon Privé is just down the road from me and was a brilliant way to go and meet some potential new clients. With the added benefit of getting to see…",
      "link": "https://www.linkedin.com/posts/charles-rolls-639589103_salon-privé-is-just-down-the-road-from-me-activity-7450568800845967360-ECj_",
      "activity_status": null
    },
    {
      "title": "Three bookings in. Momentum speaks. Renault returns to Future Stores  Stores for its third activation. This time showcasing the new Renault 5 Turbo…",
      "link": "https://www.linkedin.com/posts/engin-celikbas-9ba32a_three-bookings-in-momentum-speaks-renault-activity-7451615888421801985-nboV",
      "activity_status": null
    },
    {
      "title": "We’re excited to be exhibiting at ExCeL London on 22–23 April mediagroupdigital will be showcasing some truly ground-breaking technology — fully…",
      "link": "https://www.linkedin.com/posts/dean-brettle-72944a63_retailtechnologyshow-rts2026-retailtech-activity-7450111104761872384-wWi3",
      "activity_status": null
    },
    {
      "title": "A plot twist I wouldn't have guessed but one I am very, very happy with. Last October, I joined Lee Tayler and The Lions' Den team to lead marketing…",
      "link": "https://www.linkedin.com/posts/laurie-mcallister_ooh-marketing-sauna-activity-7451906238893903872-9CdY",
      "activity_status": null
    },
    {
      "title": "We’re pleased to see Investec back at LCY with their latest campaign on the Departure Lounge Digital Network, featuring four full-motion creatives…",
      "link": "https://www.linkedin.com/posts/london-city-airport-media-sales-568a8017a_investec-airportmedia-digitalooh-activity-7452306408714260481-aUmI",
      "activity_status": null
    },
    {
      "title": "This week FIBO 2026 in Cologne 💪 📍 Find me: Hall 5.2 | FRAMEN Booth B26 🗓️ When: April 16–17 We’re right in the heart of brands such as DRYLL…",
      "link": "https://www.linkedin.com/posts/dimitrigaertner_this-week-fibo-2026-in-cologne-find-activity-7449359643602178048-mOr8",
      "activity_status": null
    },
    {
      "title": "Imagine if you could #dooh… oh wait you can. But should you. Well if you don’t, your #advert may just slip onto the naughty step of being…",
      "link": "https://www.linkedin.com/posts/toby-ginn_dooh-advert-doohbetter-activity-7448565481508311040-XDgN",
      "activity_status": null
    },
    {
      "title": "Love what Mediascope continues to do with our product as part of their Digital Playgrounds series! Modular and configurable #experiential…",
      "link": "https://www.linkedin.com/posts/jayleedy_experiential-brandactivations-beseen-activity-7449803404966551552-Mb08",
      "activity_status": null
    },
    {
      "title": "Congratulations to Tim Waldron Barry Frey & team on a fantastic DPAA Townhall at the iconic London Transport Museum in Covent Garden. Great line up…",
      "link": "https://www.linkedin.com/posts/adrian-skelton-9b105816_ooh-dooh-dpaa-activity-7442860126417498113-ErWq",
      "activity_status": null
    },
    {
      "title": "Our team Amanda Benachour, Tommy Higgins and Camille Andrews spent the afternoon learning, collaborating and networking at the DPAA Town Hall…",
      "link": "https://www.linkedin.com/posts/london-city-airport-media-sales-568a8017a_our-team-amanda-benachour-tommy-higgins-activity-7442934747615526914-cLZQ",
      "activity_status": null
    },
    {
      "title": "Right from the start, Ian Holdcroft and I talked about inspiring the business leaders of today with Ernest Shackleton’s leadership lessons from a…",
      "link": "https://www.linkedin.com/posts/martin-brooks-frgs-73a5725_right-from-the-start-ian-holdcroft-and-i-activity-7446104261748420608-1m57",
      "activity_status": null
    },
    {
      "title": "I would like to encourage all our DPAA members in the UK and Europe to join our Research & Technology this week. We will be joined by Vistar Media's…",
      "link": "https://www.linkedin.com/posts/tim-waldron-00090757_ai-ooh-machinelearning-activity-7180581047212916737-DKSF",
      "activity_status": null
    }
  ],
  "similarly_named_profiles": [
    {
      "name": "Tim Waldron",
      "link": "https://uk.linkedin.com/in/tim-waldron-2779627a",
      "summary": "Head of Equality, Diversity & Human Rights for Midlands & Lancashire Commissioning Support Unit",
      "location": "Wakefield"
    },
    {
      "name": "Tim Waldron",
      "link": "https://www.linkedin.com/in/tim-waldron-3443165",
      "summary": "Chief Revenue Officer | Growth Accelerator | Team Builder | Market Developer",
      "location": "Lafayette, LA"
    },
    {
      "name": "Tim Waldron",
      "link": "https://www.linkedin.com/in/tim-waldron-94600b62",
      "summary": "Information Technology Technical Support at NTT DATA Services - CommonSpirit Health",
      "location": "Bakersfield, CA"
    },
    {
      "name": "Tim Waldron",
      "link": "https://www.linkedin.com/in/tim-waldron-a5142043",
      "summary": "Owner, Met Associates",
      "location": "St Peters, MO"
    },
    {
      "name": "Tim Waldron",
      "link": "https://www.linkedin.com/in/timothywaldron",
      "summary": "Institutional Sales Management",
      "location": "New York City Metropolitan Area"
    },
    {
      "name": "Tim Waldron",
      "link": "https://uk.linkedin.com/in/tim-waldron-33586270",
      "summary": "Teacher at school",
      "location": "Swindon"
    },
    {
      "name": "Tim Waldron",
      "link": "https://uk.linkedin.com/in/tim-waldron-3ba4306b",
      "summary": "warehouse assistant at bottle green",
      "location": "Gloucester"
    },
    {
      "name": "Tim Waldron",
      "link": "https://uk.linkedin.com/in/timwaldron",
      "summary": "Public lawyer helping parents and children",
      "location": "Chilworth"
    }
  ],
  "articles": [],
  "groups": [],
  "skills": [],
  "inferred_salary": null,
  "gender": null,
  "birth_date": null,
  "industry": null,
  "extra": null,
  "interests": [],
  "personal_emails": [],
  "personal_numbers": [],
  "meta": {
    "thin_profile": false,
    "last_updated": "2026-05-06T00:00:00Z"
  }
}