{
  "public_identifier": "sarahlparkes",
  "profile_pic_url": null,
  "background_cover_image_url": "https://assets.enrichlayer.com/ll/D4E16AQEwXfWUg9uxXQ/profile-displaybackgroundimage-shrink_200_800/profile-displaybackgroundimage-shrink_200_800/0/1697204302148?e=2147483647&v=beta&t=v5ctQ0kHGUSBQcjfwp1QHMtoQu6hCsHbDZ0zTH1H-bY",
  "first_name": "Sarah",
  "last_name": "Parkes",
  "full_name": "Sarah Parkes",
  "follower_count": 3896,
  "occupation": null,
  "headline": null,
  "summary": null,
  "location_str": "United Kingdom",
  "country": "GB",
  "country_full_name": "United Kingdom",
  "city": null,
  "state": null,
  "experiences": [],
  "education": [],
  "languages": [],
  "languages_and_proficiencies": [],
  "accomplishment_organisations": [],
  "accomplishment_publications": [],
  "accomplishment_honors_awards": [],
  "accomplishment_patents": [],
  "accomplishment_courses": [],
  "accomplishment_projects": [],
  "accomplishment_test_scores": [],
  "volunteer_work": [],
  "certifications": [],
  "connections": 3060,
  "people_also_viewed": [
    {
      "link": "https://www.linkedin.com/in/sharonspencer",
      "name": "Sharon Spencer MBA",
      "summary": "IT and Programme Director",
      "location": "Wendover"
    },
    {
      "link": "https://www.linkedin.com/in/francesquirke",
      "name": "Frances Quirke",
      "summary": null,
      "location": ""
    },
    {
      "link": "https://www.linkedin.com/in/dr-gill-stewart-obe-88820812",
      "name": "Dr. Gill Stewart OBE",
      "summary": "Interested in education and skills.",
      "location": "Glasgow"
    },
    {
      "link": "https://www.linkedin.com/in/conormcnicholas",
      "name": "Conor McNicholas",
      "summary": "// consultant // setting exec teams up for success // managing creative teams // helping you start right with AI // content and brand strategy // music + pop culture",
      "location": "London"
    },
    {
      "link": "https://www.linkedin.com/in/paulgpearson",
      "name": "Paul Pearson MBA... Turnaround Specialist/Business Mentor/Advisor",
      "summary": "Guiding Business Leaders to Achieve Their Dream of Success, increasing revenue with consistent monthly profit growth & financial stability and more free time to enjoy the fruits of that success. Guaranteed!",
      "location": "Nottingham"
    },
    {
      "link": "https://www.linkedin.com/in/timothyplbarnes",
      "name": "Timothy Barnes",
      "summary": "Starting things - Public policy - Education",
      "location": "London"
    },
    {
      "link": "https://www.linkedin.com/in/rubenkostucki",
      "name": "Ruben Kostucki",
      "summary": "Serial Founder & Sales Leader | GTM Engineer (Clay)",
      "location": "London"
    },
    {
      "link": "https://www.linkedin.com/in/flaviobishopcabral",
      "name": "Flavio Bishop Cabral",
      "summary": null,
      "location": "London"
    },
    {
      "link": "https://www.linkedin.com/in/johnheap",
      "name": "John Heap",
      "summary": "Webmaster and social media coordinator",
      "location": "Leeds"
    },
    {
      "link": "https://www.linkedin.com/in/richard-elwell-7470567",
      "name": "Richard Elwell",
      "summary": "Transform anxiety into high performance in less than 3hrs with our self reflective process",
      "location": "Worcester"
    },
    {
      "link": "https://www.linkedin.com/in/nickolive",
      "name": "Nick Olive",
      "summary": "Operations Lead and Business Development Director",
      "location": "London"
    },
    {
      "link": "https://www.linkedin.com/in/deepak-swaroop-uk",
      "name": "Deepak Swaroop",
      "summary": "Advisor on AI/Automation and Teacher of Mathematics",
      "location": "London"
    },
    {
      "link": "https://www.linkedin.com/in/sarahbrockwell",
      "name": "Sarah (Brockwell) Plummer",
      "summary": "Director at sarahBee marketing ltd.   |   multi award-winning PR and marketing consultant",
      "location": "Great Dunmow"
    },
    {
      "link": "https://www.linkedin.com/in/alovatt",
      "name": "Andy Lovatt",
      "summary": "Recently retired Founder of Digital Advantage and the Digital Independent Specialist College (DISC) Manchester.",
      "location": "Manchester"
    },
    {
      "link": "https://www.linkedin.com/in/david-foster-5281a611",
      "name": "David Foster",
      "summary": null,
      "location": "Bristol"
    },
    {
      "link": "https://www.linkedin.com/in/steve-jewell-4a66a911",
      "name": "Steve Jewell",
      "summary": null,
      "location": "Coventry"
    },
    {
      "link": "https://www.linkedin.com/in/dr-gill-stewart-88820812",
      "name": "Dr. Gill Stewart",
      "summary": "Interested in education and skills.",
      "location": "Glasgow"
    },
    {
      "link": "https://www.linkedin.com/in/tim-gibson-b49b6427",
      "name": "Tim Gibson",
      "summary": "Chair | Private Equity | Non-Executive Director | Advisor & Mentor driving strategy, transformation and value creation across consumer-led businesses",
      "location": "Chalfont St Giles"
    },
    {
      "link": "https://www.linkedin.com/in/keith-lilley-43181128",
      "name": "Keith Lilley",
      "summary": "The University of Canterbury•2K followers",
      "location": "Christchurch"
    },
    {
      "link": "https://www.linkedin.com/in/michele-farmer-b9a9803a",
      "name": "Michele Farmer",
      "summary": "CEO at Go Beyond",
      "location": ""
    },
    {
      "link": "https://www.linkedin.com/in/nazneen-ihtesham-90997a71",
      "name": "Nazneen Ihtesham",
      "summary": "Education Management Professional",
      "location": "Lahore District"
    },
    {
      "link": "https://www.linkedin.com/in/khalidkadri",
      "name": "Khalid Kadri",
      "summary": "Finance Professional | Product & Data-Driven Strategist | Bridging Accounting, Product Management & Data Science to Deliver Impact 🚀 | #Finance #ProductManagement #DataScience #ACCA",
      "location": "London"
    }
  ],
  "recommendations": [
    "Nanette Gibb\n\nSarah and I were colleagues within the Hearst group during a period of unprecedented pressure and challenge on traditonal ways of doing things and on delivering profitable revenues. What you see is what you get with Sarah - drive, commitment, professionalism, commercial focus, passion, humour, common sense, strong values and integrity and a huge amount of valuable industry knowledge and experience.",
    "Darren Wray\n\nI worked with Sarah for three years, and found her to be a very hard working with a length and breadth of experience of the print and publishing sector that is very impressive, this combined with her networking skills makes her powerful force in the publishing sector.Sarah is a very well organised, and detail orientated person, this helps her understand processes from different disciplines identifying the advantages to her organisation or clients quickly and efficiently.As a senior executive I found Sarah to be focused, driven and personable. In her dealings with clients Sarah brought her business acumen, knowledge of the sector, and sense of humour to form strong client relationships.I wish Sarah every success in her future career, which I have no doubt will continue to go from strength to strength."
  ],
  "activities": [
    {
      "title": "Big news from blowUP media UK! We have launched a dedicated UK LinkedIn page, built for the brands and cultural moments shaping Britain’s streets.…",
      "link": "https://www.linkedin.com/posts/blowup-media_big-news-from-blowup-media-uk-we-have-activity-7436712463678672896-W0PW",
      "activity_status": null
    },
    {
      "title": "Delighted to be joining LADbible Group as CFO of LBG Media plc at such an exciting time. Looking forward to working with Solly Solomou and the…",
      "link": "https://www.linkedin.com/posts/darren-singer-3470b020_delighted-to-be-joining-ladbible-group-as-activity-7436432476677312512-3D7U",
      "activity_status": null
    },
    {
      "title": "𝗦𝗨𝗣𝗘𝗥 𝗠𝗔𝗡 𝗗𝗘𝗭𝗘 𝗦𝗔𝗠𝗘𝗡𝗪𝗘𝗥𝗞𝗜𝗡𝗚! Samen met Ocean Outdoor Nederland en Talon_NL brachten we Joseph Klibansky letterlijk naar the…",
      "link": "https://nl.linkedin.com/posts/o₂h-creative-solutions_𝗦𝗨𝗣𝗘𝗥-𝗠𝗔𝗡-𝗗𝗘𝗭𝗘-𝗦𝗔𝗠𝗘𝗡𝗪𝗘-activity-7442857862910988290-VQ6h",
      "activity_status": null
    },
    {
      "title": "This one was very good for the soul.  I couldn’t have asked for a better finish to @AdvertisingWeekEurope.  Two brilliant entrepreneurial brands.…",
      "link": "https://www.linkedin.com/posts/helen-weisinger-a039333_this-one-was-very-good-for-the-soul-i-couldn-activity-7443337491878694913-Zzit",
      "activity_status": null
    },
    {
      "title": "A few of key take-outs from my favourite session hosted by Talon at Advertising Week 2026: \"No one channel works in isolation.\" The best OOH doesn't…",
      "link": "https://www.linkedin.com/posts/hannah-ainsworth_why-real-world-presence-has-never-mattered-activity-7442883228304166912-gMVX",
      "activity_status": null
    },
    {
      "title": "Super proud of what’s happening here ⬇️ We’re putting our money where our mouth is 💪 We’re incredibly passionate about finding and nurturing…",
      "link": "https://www.linkedin.com/posts/miriam-moertl-059ab970_super-proud-of-whats-happening-here-we-activity-7443263666004774915-2lZX",
      "activity_status": null
    },
    {
      "title": "Calling all Freelance Senior Full Stack Developers! 🚀 We have a new freelance opportunity, and we’re on the hunt for a talented Senior Full Stack…",
      "link": "https://www.linkedin.com/posts/grand-visual_calling-all-freelance-senior-full-stack-developers-activity-7443235437399339008-GWYw",
      "activity_status": null
    },
    {
      "title": "This was me with my first cab Full of hair and full of dreams I didn’t know where it would take me but I knew one thing I loved the trade There’s…",
      "link": "https://www.linkedin.com/posts/asher-moses-3970856_this-was-me-with-my-first-cab-full-of-hair-activity-7442932926926700544-4v0U",
      "activity_status": null
    },
    {
      "title": "I’ve been resisting posting on LinkedIn and leaning into other platforms for the last couple of years. Honestly, I built my entire digital…",
      "link": "https://www.linkedin.com/posts/jessicadavies1_ive-been-resisting-posting-on-linkedin-and-activity-7442854033985462272-iMJb",
      "activity_status": null
    },
    {
      "title": "Be More Parrot 🦜 Škoda Ireland is making the most of its long-term presence at Dublin Airport for what may be Ireland’s biggest football moment in…",
      "link": "https://www.linkedin.com/posts/talon-ireland_be-more-parrot-škoda-ireland-is-making-activity-7442884344261578752-EeUG",
      "activity_status": null
    },
    {
      "title": "Great article - a reminder the most effective OOH goes beyond reach and formats, showing up with cultural relevance, authentic presence, and human…",
      "link": "https://www.linkedin.com/posts/sarahlparkes_effective-ooh-contains-human-lessons-for-activity-7463171404079878144-z45n",
      "activity_status": null
    },
    {
      "title": "Great to see Talon's first nationwide OOH campaign with Revive Active. A contextually-driven campaign that aligns product messaging with consumers’…",
      "link": "https://www.linkedin.com/posts/sarahlparkes_revive-active-targets-customers-with-national-activity-7461051248910229504-xLxP",
      "activity_status": null
    },
    {
      "title": "It’s back.. WACL Festival of Talent is happening on 13th May, offering live sessions in London at Google’s King’s Cross campus, as well as in…",
      "link": "https://www.linkedin.com/posts/sarahlparkes_its-back-wacl-festival-of-talent-is-happening-activity-7449764295350976512-rZpQ",
      "activity_status": null
    },
    {
      "title": "Such a fab evening and so uplifting to hear the support from our wonderful male allies. Equality is everyone’s business and it’s good for all our…",
      "link": "https://www.linkedin.com/posts/sarahlparkes_wacl-genderequality-activity-7445482672216322050-79Kh",
      "activity_status": null
    },
    {
      "title": "This is an incredible achievement. Such a worthy recognition of how awesome Team Talon is. 🙌🏻🙌🏻",
      "link": "https://www.linkedin.com/posts/sarahlparkes_this-is-an-incredible-achievement-such-activity-7440773817808932864-IWfS",
      "activity_status": null
    },
    {
      "title": "It is nearly that time of year when I have the pleasure of judging #CampaignUK's 40 over 40! Always so inspiring to read everyone's stories and…",
      "link": "https://www.linkedin.com/posts/sarahlparkes_campaignuk-activity-7432457824137338880-E58T",
      "activity_status": null
    },
    {
      "title": "Exciting news and great to see Talon shortlisted for Campaign UK’s independent media agency of the year.. 🙌🏻🙌🏻",
      "link": "https://www.linkedin.com/posts/sarahlparkes_exciting-news-and-great-to-see-talon-shortlisted-activity-7424872016366919680-9Hgg",
      "activity_status": null
    },
    {
      "title": "A shout out to all women in senior roles in the Out of Home Advertising industry (Chief, Board, or Executive level) and World Out of Home…",
      "link": "https://www.linkedin.com/posts/sarahlparkes_a-shout-out-to-all-women-in-senior-roles-activity-7419393187846189057-Nd5d",
      "activity_status": null
    },
    {
      "title": "This really captures the opportunity for experiential, OOH and retail media. The creativity has never been stronger — but without shared measurement…",
      "link": "https://www.linkedin.com/posts/sarahlparkes_ooh-retailmedia-activity-7414029219065700352-Pdnp",
      "activity_status": null
    },
    {
      "title": "A fantastic opportunity to join the leadership team at Clays. If you are a strategic, creative and commercially minded marketer who can balance brand…",
      "link": "https://www.linkedin.com/posts/sarahlparkes_director-of-marketing-at-clays-support-office-activity-7407188887304949760-s6dt",
      "activity_status": null
    },
    {
      "title": "Brilliant article from Ryan Laul #OOH is powerful on its own, but it becomes even more impactful when integrated across platforms—bringing physical…",
      "link": "https://www.linkedin.com/posts/sarahlparkes_ooh-ooh-dooh-activity-7399540962747760640-pFOn",
      "activity_status": null
    },
    {
      "title": "🎄 A Wednesday night well spent catching up on this year’s Christmas ads - and what a mix it is. So great to see the usual tear-jerkers although not…",
      "link": "https://www.linkedin.com/posts/sarahlparkes_christmasads-creative-ooh-activity-7392155962339508224-FL4e",
      "activity_status": null
    },
    {
      "title": "Thank you Katrin A. Robertson. Looking forward to getting involved and supporting World Out of Home Organization’s Women in WOO network. #womeninooh",
      "link": "https://www.linkedin.com/posts/sarahlparkes_womeninooh-activity-7391587307667222529-1JYt",
      "activity_status": null
    },
    {
      "title": "What a dream team Steven Heylen Jérémie Chryssanthos Golfidis .. Talon Belux #ooh #dooh 🙌🏻",
      "link": "https://www.linkedin.com/posts/sarahlparkes_talon-belux-is-ready-to-meet-your-brand-activity-7386830419490443265-iMAj",
      "activity_status": null
    },
    {
      "title": "What a fantastic partnership - Danielle Austin Evolve OOH and the formidable Gill Reid .. exciting times ahead. #ooh #dooh",
      "link": "https://www.linkedin.com/posts/sarahlparkes_ooh-dooh-activity-7379591275332673536-HJRY",
      "activity_status": null
    },
    {
      "title": "Great to have you fully on board with all things Talon at your fingertips #ooh #dooh",
      "link": "https://www.linkedin.com/posts/sarahlparkes_ooh-dooh-activity-7378352821215141888-8JrG",
      "activity_status": null
    },
    {
      "title": "Welcome to the Talon Out of Home Masters family Menno van der Hoeven .. Looking forward to working together 🙌🏻🙌🏻 #ooh #dooh",
      "link": "https://www.linkedin.com/posts/sarahlparkes_menno-van-der-hoeven-client-lead-out-of-home-activity-7355959677324533762-P4IO",
      "activity_status": null
    },
    {
      "title": "What a talented team Luke Willbourn Welcome Shanil Chande - exciting times ahead! https://lnkd.in/ezvabMrM",
      "link": "https://www.linkedin.com/posts/sarahlparkes_what-a-talented-team-luke-willbourn-welcome-activity-7355627572719689728-J4sv",
      "activity_status": null
    },
    {
      "title": "Our Group CEO Sue Frogley reflects on her first year at Talon with Sonoo Singh at Creative Salon Worldwide. It has been an action packed year and…",
      "link": "https://www.linkedin.com/posts/sarahlparkes_sue-frogleys-next-act-reimagining-talon-activity-7354544380315062273-d1Hi",
      "activity_status": null
    },
    {
      "title": "Welcome Jérémie Chryssanthos Golfidis . Dream team 🙌🏻🙌🏻",
      "link": "https://www.linkedin.com/posts/sarahlparkes_media-marketing-news-talon-treedt-toe-activity-7350616385607110657-0Z5U",
      "activity_status": null
    },
    {
      "title": "#WACL and our #ChangeTheStats campaign is now LIVE at Cannes 💥 The work starts with #ChangingTheLanguageofLeadership and that was the hero topic of…",
      "link": "https://www.linkedin.com/posts/sarahlparkes_changethestats-playbookpdf-activity-7340990758843310080-Vnms",
      "activity_status": null
    },
    {
      "title": "Congratulations to our visionary founder Eric Newnham .. a worthy recognition for all Eric has achieved in the glorious world of OOH! As Tina would…",
      "link": "https://www.linkedin.com/posts/sarahlparkes_congratulations-to-our-visionary-founder-activity-7336708446618075136-0Rtp",
      "activity_status": null
    },
    {
      "title": "HUGE news. Jeremy Male will be supporting Ryan Laul and our North American leadership team to turbo charge the momentum we have already built in…",
      "link": "https://www.linkedin.com/posts/sarahlparkes_thinkoutside-activity-7336152986966011905-9gMy",
      "activity_status": null
    },
    {
      "title": "Final judging of the #Grand Indies - some outstanding creative work from the Worldwide Partners, Inc. agencies - looking forward to May and…",
      "link": "https://www.linkedin.com/posts/sarahlparkes_grand-grandindies-wpigrandindes-activity-7305239409036005378-41sp",
      "activity_status": null
    },
    {
      "title": "Welcome to the Talon family Cornelie Weller - looking forward to building on such great foundations together - it's going to be FUN! And Frank H.…",
      "link": "https://www.linkedin.com/posts/sarahlparkes_welcome-to-the-talon-family-cornelie-weller-activity-7303369710018936833-M8RO",
      "activity_status": null
    },
    {
      "title": "Really looking forward to seeing this year's Campaign UK's 40Over40 nominations. With just over 3 weeks until the standard deadline on Thursday 3rd…",
      "link": "https://www.linkedin.com/posts/sarahlparkes_campaign40over40-activity-7305546630944948224-6EMA",
      "activity_status": null
    },
    {
      "title": "Creativity : Experiential : Out of Home #OOH In a world flooded with digital noise, creativity that exists outside the screen is more impactful than…",
      "link": "https://www.linkedin.com/posts/sarahlparkes_ooh-activity-7292266071217098753-TSgB",
      "activity_status": null
    },
    {
      "title": "London in the Spotlight! ✨🇬🇧 Great event last night with JCDecaux UK unveiling its vision to install 1,000 new data-driven digital screens across…",
      "link": "https://www.linkedin.com/posts/sarahlparkes_london-ooh-dooh-activity-7292815568825438210-J0AB",
      "activity_status": null
    },
    {
      "title": "Welcome to the Talon family Out of Home Masters. Looking forward to working together 🎉🎉 Frank H. Hardenberg Yordi Hardenberg Rick Vriesema Sandra…",
      "link": "https://www.linkedin.com/posts/sarahlparkes_welcome-to-the-talon-family-out-of-home-masters-activity-7287451247874310144-W7uV",
      "activity_status": null
    },
    {
      "title": "Exciting News at Grand Visual! Andrew Pearson has joined our North America team as SVP - Creative Strategy🎉 We couldn’t be more excited about the…",
      "link": "https://www.linkedin.com/posts/sarahlparkes_newhire-grandvisual-ooh-activity-7288486070143340544-lNZu",
      "activity_status": null
    },
    {
      "title": "Dream team assemble! Delighted to be part of such a great team redefining what OOH can achieve for brands worldwide. Let's do this! #ooh #dooh",
      "link": "https://www.linkedin.com/posts/sarahlparkes_ooh-dooh-activity-7285665019395014656-rl-Q",
      "activity_status": null
    },
    {
      "title": "Our brilliant creative team Grand Visual are looking for a Junior Creative Strategist to drive creativity and innovation. This role is perfect for a…",
      "link": "https://www.linkedin.com/posts/sarahlparkes_junior-creative-strategist-grand-visual-activity-7221592293164679171-0fyO",
      "activity_status": null
    },
    {
      "title": "Great article from Emily Alcorn .. Explaining how #OOH advertising, with its innovative use of data and dynamic content, sets the standard for…",
      "link": "https://www.linkedin.com/posts/sarahlparkes_ooh-activity-7214337439065141248-k_-u",
      "activity_status": null
    },
    {
      "title": "Thanks Pesach Lattin for the platform to highlight ooh's superpowers... #ooh #dooh",
      "link": "https://www.linkedin.com/posts/sarahlparkes_gas-pumps-and-elevators-unlikely-heroes-activity-7173791845729095680-jsru",
      "activity_status": null
    },
    {
      "title": "Brilliant news 🎉🎉",
      "link": "https://www.linkedin.com/posts/sarahlparkes_brilliant-news-activity-7213476007696052224-G9q9",
      "activity_status": null
    },
    {
      "title": "So looking forward to all the brilliant sessions and exciting meetings and events we have planned. #oohevangelists",
      "link": "https://www.linkedin.com/posts/sarahlparkes_oohevangelists-activity-7206265391017291776-Ffkh",
      "activity_status": null
    },
    {
      "title": "Such great news. Welcome Ryan Laul to the Talon family - really looking forward to working together. Exciting times ahead! #ooh #winningteam",
      "link": "https://www.linkedin.com/posts/sarahlparkes_ooh-winningteam-activity-7203835639039963137-aJAj",
      "activity_status": null
    },
    {
      "title": "So great to be recognised as one of the Top 100 places to work.. Talon is a very special place and this proves it!",
      "link": "https://www.linkedin.com/posts/sarahlparkes_so-great-to-be-recognised-as-one-of-the-top-activity-7196154685328707586-tGEo",
      "activity_status": null
    },
    {
      "title": "In today's business landscape, achieving clarity in strategy is essential for growth. Companies like Costco, Salesforce, Amazon, and Patagonia…",
      "link": "https://www.linkedin.com/posts/sarahlparkes_to-decide-where-to-grow-next-pinpoint-what-activity-7187813042942803968-N0KH",
      "activity_status": null
    },
    {
      "title": "Exciting news indeed 🙌🏻",
      "link": "https://www.linkedin.com/posts/sarahlparkes_exciting-news-indeed-activity-7176244301411037185-Fhaq",
      "activity_status": null
    },
    {
      "title": "What a show! We were thrilled to partner with Pepsi, Grand Visual, SKYMAGIC Drone Shows, and ODM UK to deliver an extraordinary drones light show for…",
      "link": "https://www.linkedin.com/posts/sarahlparkes_talon-pepsi-thirstyformore-activity-7177984828305215488-ncwm",
      "activity_status": null
    },
    {
      "title": "Thanks Rachel Forde for sharing. Couldn’t agree more. It’s our responsibility to make change - we can all make a difference. #equality",
      "link": "https://www.linkedin.com/posts/sarahlparkes_barbie-the-dream-gap-project-activity-7177632946835607553-sU88",
      "activity_status": null
    },
    {
      "title": "What a fantastic evening celebrating such wonderful and inspirational women. HUGE congrats to all...",
      "link": "https://www.linkedin.com/posts/sarahlparkes_campaign-inspiring-women-awards-2024-winners-activity-7171822664301301760-Iqap",
      "activity_status": null
    },
    {
      "title": "Brilliant news .. 👏🏻 👏🏻 Enza Chiodi Laura Colona",
      "link": "https://www.linkedin.com/posts/sarahlparkes_brilliant-news-enza-chiodi-laura-activity-7170831792021688321-6PVR",
      "activity_status": null
    },
    {
      "title": "Thank you Out There 360 - we are super excited to partner with you. We are going to create some amazing #ooh campaigns together!",
      "link": "https://www.linkedin.com/posts/sarahlparkes_ooh-activity-7166208359057076225-huCB",
      "activity_status": null
    },
    {
      "title": "A new report from Outsmart finds that OOH advertising is the most sustainable compared to other major media. According to KPMG's research, OOH…",
      "link": "https://www.linkedin.com/posts/sarahlparkes_ooh-most-sustainable-ad-platform-outsmart-activity-7193547031624265732-ifG-",
      "activity_status": null
    },
    {
      "title": "Today has been a whirlwind and a tad surreal BUT so happy that I got to extol the virtues of #ooh on BBC News this morning #ooh #dooh #Superbowl…",
      "link": "https://www.linkedin.com/posts/sarahlparkes_ooh-ooh-dooh-activity-7161451525888696321-fXV6",
      "activity_status": null
    },
    {
      "title": "So chuffed Talon have been shortlisted in Campaign UK’s Independent Agency of the Year. Thank you to all our wonderful clients, partners and the very…",
      "link": "https://www.linkedin.com/posts/sarahlparkes_so-chuffed-talon-have-been-shortlisted-in-activity-7160757452517359616-oqNc",
      "activity_status": null
    },
    {
      "title": "Looking forward to sharing the stage and continuing the #ooh conversation with these brilliant panellists..",
      "link": "https://www.linkedin.com/posts/sarahlparkes_ooh-activity-7120496895348609024-QRG1",
      "activity_status": null
    },
    {
      "title": "I am excited to be speaking at \"The Future of Media\" later today. The future of any industry - including marketing - depends on intentional…",
      "link": "https://www.linkedin.com/posts/sarahlparkes_futureofmedia-adwanted-marketing-activity-7117830114226130945-uzIk",
      "activity_status": null
    },
    {
      "title": "Really looking forward to working with The Kite Factory to deliver brilliant client solutions #creative #ooh #dooh",
      "link": "https://www.linkedin.com/posts/sarahlparkes_the-kite-factory-selects-talon-as-ooh-partner-activity-7064196482895081472-kafO",
      "activity_status": null
    },
    {
      "title": "Love this initiative, harnessing the reach of #OOH! So great to see City Outdoor Media using their platform to offer positive messaging long term.…",
      "link": "https://www.linkedin.com/posts/sarahlparkes_city-outdoor-and-steven-bartlett-spread-the-activity-6986633777695318016-wLTE",
      "activity_status": null
    },
    {
      "title": "What a fantastic session this was. #ooh #media #adtech Barry Cupples James Copley",
      "link": "https://www.linkedin.com/posts/sarahlparkes_ooh-media-adtech-activity-6904400707571838976-EtkC",
      "activity_status": null
    }
  ],
  "similarly_named_profiles": [
    {
      "name": "Sarah Parkes",
      "link": "https://uk.linkedin.com/in/sarah-parkes-73383b31",
      "summary": "Helping entrepreneurial parents have a calmer, happier relationship with your child. Using successful gentle approaches 1:1, 2:1 & groups. 12 mth packages from £1,111. Reduce tantrums|meltdowns|overwhelm",
      "location": "Greater Edinburgh Area"
    },
    {
      "name": "Sarah Parkes",
      "link": "https://uk.linkedin.com/in/sarah-parkes-69a61184",
      "summary": "Business Owner at Daisy Corner lodge secret getaway",
      "location": "United Kingdom"
    },
    {
      "name": "Sarah Parkes",
      "link": "https://uk.linkedin.com/in/sarah-parkes-display-expo",
      "summary": "parkesexpo.com ★ Helping you connect with your client's ★ ★ Print & Marketing Collateral ★ Branded Packaging ★ Promo Gifts ★ Exhibition Design & Build ★ Displays",
      "location": "Biggleswade"
    },
    {
      "name": "Sarah Parkes",
      "link": "https://uk.linkedin.com/in/sarah-parkes-033700ba",
      "summary": "Onboarding & Financial Crime Analyst",
      "location": "United Kingdom"
    },
    {
      "name": "Sarah P.",
      "link": "https://uk.linkedin.com/in/sarah-p-a06370",
      "summary": "Senior Cloud Solution Architect @ Microsoft | Solution Architecture",
      "location": "Greater Reading Area"
    },
    {
      "name": "Sarah Parkes",
      "link": "https://uk.linkedin.com/in/sarah-parkes-445b351a0",
      "summary": "Human Resources Director & Business Consultant at Sparx Business Solutions. Holiday home owner at Surf View. Skin care Ambassador at Tropic skin care. Trustee at God First Church.",
      "location": "Cheltenham"
    },
    {
      "name": "Sarah Parkes",
      "link": "https://uk.linkedin.com/in/sarahparkescoaching",
      "summary": "Helping professional parents have a calmer, happier family life, by reducing your kids anxiety, tantrums & meltdowns. Using effective gentle strategies group|individual|couple|organisational support from £97",
      "location": "Greater Edinburgh Area"
    },
    {
      "name": "Sarah Parkes",
      "link": "https://uk.linkedin.com/in/sarah-parkes-ba815819",
      "summary": "Property Programme Manager at Solihull Metropolitan Borough Council",
      "location": "Warwick"
    }
  ],
  "articles": [],
  "groups": [],
  "skills": [],
  "inferred_salary": null,
  "gender": null,
  "birth_date": null,
  "industry": null,
  "extra": null,
  "interests": [],
  "personal_emails": [],
  "personal_numbers": [],
  "meta": {
    "thin_profile": true,
    "last_updated": "2026-05-29T04:53:17Z"
  }
}