{
  "public_identifier": "aybike-özdurgut-sarar-628a8ab8",
  "profile_pic_url": "https://assets.enrichlayer.com/pp/profilepic/2088893044fcba8d1d5bda21fb8ff4eb",
  "background_cover_image_url": "https://assets.enrichlayer.com/pp/profilepic/60c6015ee2519c056444fbd033145b42",
  "first_name": "AYBİKE",
  "last_name": "ÖZDURGUT SARAR",
  "full_name": "AYBİKE ÖZDURGUT SARAR",
  "follower_count": 627,
  "occupation": "Global Media Lead at Outmedya",
  "headline": "GLOBAL MEDIA LEAD",
  "summary": null,
  "location_str": "Istanbul, Turkey",
  "country": "TR",
  "country_full_name": "Turkey",
  "city": "Istanbul, Turkey",
  "state": "Istanbul",
  "experiences": [
    {
      "starts_at": {
        "day": 1,
        "month": 1,
        "year": 2024
      },
      "ends_at": null,
      "company": "Outmedya",
      "company_linkedin_profile_url": "https://www.linkedin.com/company/outmedya",
      "company_facebook_profile_url": null,
      "title": "Global Media Lead",
      "description": null,
      "location": null,
      "logo_url": null
    },
    {
      "starts_at": {
        "day": 1,
        "month": 12,
        "year": 2021
      },
      "ends_at": {
        "day": 1,
        "month": 12,
        "year": 2023
      },
      "company": "Outmedya",
      "company_linkedin_profile_url": "https://www.linkedin.com/company/outmedya",
      "company_facebook_profile_url": null,
      "title": "Global Media Manager",
      "description": null,
      "location": null,
      "logo_url": null
    },
    {
      "starts_at": {
        "day": 1,
        "month": 3,
        "year": 2019
      },
      "ends_at": {
        "day": 1,
        "month": 12,
        "year": 2020
      },
      "company": "Wavemaker",
      "company_linkedin_profile_url": "https://www.linkedin.com/company/wavemakerglobal",
      "company_facebook_profile_url": null,
      "title": "Strategist / Senior Planning Executive, Digital & Technology",
      "description": "-\tCreating, defining and implementing the digital strategy and online communication plan of the brand -\tManage digital ads campaigns that focus primarily on lead generation, to monitor the performance, offer and take actions that will increase the performance -\tPlan and manage special project for campaigns of brand -\tReporting campaigns created in line with digital marketing metrics -      Prepare and analyze competitive report -\tMaintaining client budgets and ensuring finance procedures are rigorously adhered to",
      "location": null,
      "logo_url": null
    },
    {
      "starts_at": {
        "day": 1,
        "month": 1,
        "year": 2017
      },
      "ends_at": {
        "day": 1,
        "month": 1,
        "year": 2019
      },
      "company": "OMD Turkey",
      "company_linkedin_profile_url": "https://www.linkedin.com/company/omd-turkey",
      "company_facebook_profile_url": null,
      "title": "Media Planning Executive",
      "description": "-\tUndertaking research and analyzing data using  specialist industry  resources -\tHelping to make decisions on the best form of media for specific clients and campaigns -\tApplying knowledge of media and communication  platforms to identify the most appropriate mediums for building awareness of a client's brand -\tEvaluating the effectiveness of campaigns in order to inform future campaign -Competitive analysis",
      "location": "Istanbul, Turkey",
      "logo_url": null
    },
    {
      "starts_at": {
        "day": 1,
        "month": 6,
        "year": 2015
      },
      "ends_at": {
        "day": 1,
        "month": 9,
        "year": 2015
      },
      "company": "Universal Studios Hollywood",
      "company_linkedin_profile_url": "https://www.linkedin.com/company/universal-studios-hollywood",
      "company_facebook_profile_url": null,
      "title": "Sales and Marketing",
      "description": "Work and Travel Program -Working with the sales team -Cash handling, printing and packaging products -Guest relations -Help guests select the right products to suit their needs adding borders and decals to make their photos extra special",
      "location": "Orlando, Florida Area",
      "logo_url": null
    },
    {
      "starts_at": {
        "day": 1,
        "month": 1,
        "year": 2015
      },
      "ends_at": {
        "day": 1,
        "month": 3,
        "year": 2015
      },
      "company": "Orka Holding - Damat / Tween / D'S / ADV",
      "company_linkedin_profile_url": "https://www.linkedin.com/company/orkaholding-ds-damat-tween",
      "company_facebook_profile_url": null,
      "title": "Human Resources Intern",
      "description": "-Steps in the recruiting and hiring process, including: posting job openings, reviewing resumes, conducting telephone and in-person interviews, helping make job offers.",
      "location": "İstanbul, Türkiye",
      "logo_url": null
    },
    {
      "starts_at": {
        "day": 1,
        "month": 7,
        "year": 2014
      },
      "ends_at": {
        "day": 1,
        "month": 8,
        "year": 2014
      },
      "company": "Elginkan Holding",
      "company_linkedin_profile_url": "https://www.linkedin.com/company/elginkan-holding",
      "company_facebook_profile_url": null,
      "title": "Accounting and Finance Intern",
      "description": "-Work with the account and finance team on yearly forecasting efforts -Manage the monthly tracking of their physical inventory -Support the payment processing team -Data entry -Help with month-end  financial reports",
      "location": "Bilecik, Türkiye",
      "logo_url": null
    },
    {
      "starts_at": {
        "day": 1,
        "month": 7,
        "year": 2013
      },
      "ends_at": {
        "day": 1,
        "month": 8,
        "year": 2013
      },
      "company": "Mepsan A.S.",
      "company_linkedin_profile_url": "https://www.linkedin.com/company/mepsan",
      "company_facebook_profile_url": null,
      "title": "Sales And Marketing Intern",
      "description": "-Assist in the creation of signage, circulars, e-mail campaigns, on line promotion, etc. -Assist with the preparation and delivery of training materials -Perform analysis of marketing and sales data -Seek and analyze competitor marketing and sales materials both on and offline",
      "location": "İstanbul, Türkiye",
      "logo_url": null
    }
  ],
  "education": [
    {
      "starts_at": {
        "day": 1,
        "month": 1,
        "year": 2011
      },
      "ends_at": {
        "day": 31,
        "month": 1,
        "year": 2016
      },
      "field_of_study": "İşletme (İngilizce)",
      "degree_name": null,
      "school": "İstanbul Üniversitesi",
      "school_linkedin_profile_url": "https://www.linkedin.com/school/istanbul-university",
      "school_facebook_profile_url": null,
      "description": null,
      "logo_url": null,
      "grade": null,
      "activities_and_societies": "Faaliyetler ve Topluluklar:İşletme Kulübü Ekip Üyesi\nKültür Kulübü Dans Topluluğu Ekip Üyesi"
    },
    {
      "starts_at": {
        "day": 1,
        "month": 1,
        "year": 2006
      },
      "ends_at": {
        "day": 31,
        "month": 1,
        "year": 2010
      },
      "field_of_study": null,
      "degree_name": null,
      "school": "Bozüyük Anadolu Öğretmen Lisesi",
      "school_linkedin_profile_url": null,
      "school_facebook_profile_url": null,
      "description": null,
      "logo_url": null,
      "grade": null,
      "activities_and_societies": null
    },
    {
      "starts_at": {
        "day": 1,
        "month": 1,
        "year": 2016
      },
      "ends_at": null,
      "field_of_study": null,
      "degree_name": null,
      "school": "Anadolu University",
      "school_linkedin_profile_url": "https://www.linkedin.com/school/anadoluuniv",
      "school_facebook_profile_url": null,
      "description": null,
      "logo_url": null,
      "grade": null,
      "activities_and_societies": null
    }
  ],
  "languages": [],
  "languages_and_proficiencies": [],
  "accomplishment_organisations": [],
  "accomplishment_publications": [],
  "accomplishment_honors_awards": [],
  "accomplishment_patents": [],
  "accomplishment_courses": [],
  "accomplishment_projects": [],
  "accomplishment_test_scores": [],
  "volunteer_work": [],
  "certifications": [],
  "connections": 500,
  "people_also_viewed": [],
  "recommendations": [],
  "activities": [],
  "similarly_named_profiles": [],
  "articles": [],
  "groups": [],
  "skills": [],
  "inferred_salary": null,
  "gender": null,
  "birth_date": null,
  "industry": null,
  "extra": null,
  "interests": [],
  "personal_emails": [],
  "personal_numbers": [],
  "meta": {
    "thin_profile": false,
    "last_updated": "2026-05-04T00:00:00Z"
  }
}